pcdsutils/__init__.py
pcdsutils/_version.py
pcdsutils/enum.py
pcdsutils/ext_scripts.py
pcdsutils/import_timer.py
pcdsutils/info.py
pcdsutils/json_to_table.py
pcdsutils/log.py
pcdsutils/ophyd_helpers.py
pcdsutils/profile.py
pcdsutils/release_notes.py
pcdsutils/requirements.py
pcdsutils/type_hints.py
pcdsutils/utils.py
pcdsutils/version.py
pcdsutils/qt/__init__.py
pcdsutils/qt/callbacks.py
pcdsutils/qt/designer_display.py
pcdsutils/qt/lazy.py
pcdsutils/qt/popbar.py
pcdsutils/tests/__init__.py
pcdsutils/tests/conftest.py
pcdsutils/tests/dummy_submodule.py
pcdsutils/tests/test_designer_display.py
pcdsutils/tests/test_enum.py
pcdsutils/tests/test_ext_scripts.py
pcdsutils/tests/test_import_timer.py
pcdsutils/tests/test_json_to_table.py
pcdsutils/tests/test_logging.py
pcdsutils/tests/test_ophyd.py
pcdsutils/tests/test_profile.py
pcdsutils/tests/test_requirements.py
pcdsutils/tests/test_utils.py
pcdsutils/tests/ui/test1.ui
pcdsutils/tests/ui/test2.ui
pcdsutils/tests/ui/test3.ui
pcdsutils-0.14.2.dist-info/licenses/AUTHORS.rst
pcdsutils-0.14.2.dist-info/licenses/LICENSE
pcdsutils-0.14.2.dist-info/METADATA
pcdsutils-0.14.2.dist-info/WHEEL
pcdsutils-0.14.2.dist-info/entry_points.txt
pcdsutils-0.14.2.dist-info/top_level.txt
pcdsutils-0.14.2.dist-info/RECORD
