Metadata-Version: 2.4
Name: pcdsutils
Version: 0.14.2
Summary: PCDS Python Utilities
Author: SLAC National Accelerator Laboratory
License: Copyright (c) 2023, The Board of Trustees of the Leland Stanford Junior
Classifier: Development Status :: 2 - Pre-Alpha
Classifier: Natural Language :: English
Classifier: Programming Language :: Python :: 3
Requires-Python: >=3.9
License-File: LICENSE
License-File: AUTHORS.rst
Requires-Dist: prettytable
Requires-Dist: pypandoc
Requires-Dist: pyyaml
Requires-Dist: qtpy
Requires-Dist: qtpyinheritance
Requires-Dist: requests
Requires-Dist: typing_extensions
Provides-Extra: test
Requires-Dist: ophyd; extra == "test"
Requires-Dist: pytest>=6.2.0; extra == "test"
Requires-Dist: pytest-qt; extra == "test"
Requires-Dist: pyqt5; extra == "test"
Requires-Dist: line_profiler; extra == "test"
Provides-Extra: doc
Requires-Dist: docs-versions-menu; extra == "doc"
Requires-Dist: ipython; extra == "doc"
Requires-Dist: numpydoc; extra == "doc"
Requires-Dist: sphinx; extra == "doc"
Requires-Dist: sphinx-copybutton; extra == "doc"
Requires-Dist: sphinx_rtd_theme; extra == "doc"
Requires-Dist: sphinxcontrib-jquery; extra == "doc"
Dynamic: license-file
